Dll/DmReg.dll
Dll/Reg.py
Dll/__init__.py
Dll/dm.dll
1Q847-1.1.5.dist-info/LICENSE.txt
1Q847-1.1.5.dist-info/METADATA
1Q847-1.1.5.dist-info/WHEEL
1Q847-1.1.5.dist-info/top_level.txt
1Q847-1.1.5.dist-info/RECORD
